job_pool/__init__.py
job_pool/job_pool.py
job_pool/tqdm_logger.py
job_pool-0.3.4.dist-info/LICENSE
job_pool-0.3.4.dist-info/METADATA
job_pool-0.3.4.dist-info/WHEEL
job_pool-0.3.4.dist-info/RECORD
