Metadata-Version: 2.1
Name: job-pool
Version: 0.3.4
Summary: Enhanced Job Pool for Python Multiprocessing
License: Apache-2.0
Author: Matthew The
Author-email: matthew.the@tum.de
Requires-Python: >=3.8,<4.0
Classifier: License :: OSI Approved :: Apache Software License
Classifier: Programming Language :: Python :: 3
Classifier: Programming Language :: Python :: 3.8
Classifier: Programming Language :: Python :: 3.9
Classifier: Programming Language :: Python :: 3.10
Classifier: Programming Language :: Python :: 3.11
Classifier: Programming Language :: Python :: 3.12
Requires-Dist: threadpoolctl (>=3.2.0,<4.0.0)
Requires-Dist: tqdm (>=4.66.1,<5.0.0)
